{
	"/Rbs/Review/": {
		"module": "Rbs_Review",
		"name": "home",
		"rule": {
			"redirectTo": "/Rbs/Review/Review/",
			"labelKey": "m.rbs.review.admin.module_name | ucf"
		},
		"auto": false
	},
	"/Rbs/Review/Review/": {
		"model": "Rbs_Review_Review",
		"name": "list",
		"rule": {
			"templateUrl": "Document/Rbs/Review/Review/list.twig",
			"labelKey": "m.rbs.review.admin.review_list | ucf"
		},
		"auto": true
	},
	"/Rbs/Review/Review/:id": {
		"model": "Rbs_Review_Review",
		"name": "form",
		"rule": {
			"templateUrl": "Document/Rbs/Review/Review/form.twig",
			"labelKey": "m.rbs.review.documents.review | ucf",
			"labelId": "id"
		},
		"auto": true
	},
	"/Rbs/Review/Review/new": {
		"model": "Rbs_Review_Review",
		"name": "new",
		"rule": {
			"templateUrl": "Document/Rbs/Review/Review/form.twig",
			"labelKey": "m.rbs.admin.adminjs.new_resource | ucf"
		},
		"auto": true
	}
}